tdash/__init__.py
tdash/functions.py
tdash/generators.py
tdash/timing.py
tdash-0.0.9.dist-info/DESCRIPTION.rst
tdash-0.0.9.dist-info/METADATA
tdash-0.0.9.dist-info/RECORD
tdash-0.0.9.dist-info/WHEEL
tdash-0.0.9.dist-info/metadata.json
tdash-0.0.9.dist-info/top_level.txt
