Metadata-Version: 2.0
Name: tdash
Version: 0.0.9
Summary: Collection of utils inspired by underscore and lodash. No guarantees that I will not change this on a whim
Home-page: https://github.com/eastlondoner/tdash
Author: Andrew Jefferson
Author-email: andyj.trinity@gmail.com
License: UNKNOWN
Download-URL: https://github.com/eastlondoner/tdash/tarball/0.0.9
Platform: UNKNOWN
Requires-Dist: pydash
